{"trial_id": "0007", "hyperparameters": {"space": [{"class_name": "Int", "config": {"name": "units", "default": null, "conditions": [], "min_value": 10, "max_value": 50, "step": 5, "sampling": "linear"}}, {"class_name": "Float", "config": {"name": "dropout_value", "default": 0.0, "conditions": [], "min_value": 0.0, "max_value": 0.5, "step": 0.1, "sampling": "linear"}}, {"class_name": "Choice", "config": {"name": "optimizer", "default": "rmsprop", "conditions": [], "values": ["rmsprop", "nadam", "adam"], "ordered": false}}], "values": {"units": 10, "dropout_value": 0.0, "optimizer": "adam", "tuner/epochs": 2, "tuner/initial_epoch": 0, "tuner/bracket": 4, "tuner/round": 0}}, "metrics": {"metrics": {"loss": {"direction": "min", "observations": [{"value": [0.6322268843650818], "step": 1}]}, "accuracy": {"direction": "max", "observations": [{"value": [0.6301075220108032], "step": 1}]}, "recall": {"direction": "min", "observations": [{"value": [0.6486014127731323], "step": 1}]}, "precision": {"direction": "min", "observations": [{"value": [0.7217898964881897], "step": 1}]}, "val_loss": {"direction": "min", "observations": [{"value": [0.586086094379425], "step": 1}]}, "val_accuracy": {"direction": "max", "observations": [{"value": [0.6834170818328857], "step": 1}]}, "val_recall": {"direction": "min", "observations": [{"value": [0.7241379022598267], "step": 1}]}, "val_precision": {"direction": "min", "observations": [{"value": [0.730434775352478], "step": 1}]}}}, "score": 0.6834170818328857, "best_step": 1, "status": "COMPLETED", "message": null}