{"trial_id": "0108", "hyperparameters": {"space": [{"class_name": "Int", "config": {"name": "units", "default": null, "conditions": [], "min_value": 10, "max_value": 50, "step": 5, "sampling": "linear"}}, {"class_name": "Float", "config": {"name": "dropout_value", "default": 0.0, "conditions": [], "min_value": 0.0, "max_value": 0.5, "step": 0.1, "sampling": "linear"}}, {"class_name": "Choice", "config": {"name": "optimizer", "default": "rmsprop", "conditions": [], "values": ["rmsprop", "nadam", "adam"], "ordered": false}}], "values": {"units": 45, "dropout_value": 0.4, "optimizer": "nadam", "tuner/epochs": 4, "tuner/initial_epoch": 2, "tuner/bracket": 4, "tuner/round": 1, "tuner/trial_id": "0087"}}, "metrics": {"metrics": {"loss": {"direction": "min", "observations": [{"value": [0.6113774180412292], "step": 1}]}, "accuracy": {"direction": "max", "observations": [{"value": [0.6440860033035278], "step": 1}]}, "recall": {"direction": "min", "observations": [{"value": [0.7587412595748901], "step": 1}]}, "precision": {"direction": "min", "observations": [{"value": [0.6921849846839905], "step": 1}]}, "val_loss": {"direction": "min", "observations": [{"value": [0.5655096769332886], "step": 1}]}, "val_accuracy": {"direction": "max", "observations": [{"value": [0.7437185645103455], "step": 1}]}, "val_recall": {"direction": "min", "observations": [{"value": [0.8534482717514038], "step": 1}]}, "val_precision": {"direction": "min", "observations": [{"value": [0.7443609237670898], "step": 1}]}}}, "score": 0.7437185645103455, "best_step": 1, "status": "COMPLETED", "message": null}